DESCRIPTION.rst
MANIFEST.in
README
setup.cfg
setup.py
ship/__init__.py
ship/colors.py
ship/commands.py
ship/deployer.py
ship/environment.py
ship/errors.py
ship/logger.py
ship/maven.py
ship/module.py
ship/monit.py
ship/project.py
ship/subversion.py
ship/test_acceptance_deployed.py
ship/tomcat.py
ship/validator.py
uji_ship.egg-info/PKG-INFO
uji_ship.egg-info/SOURCES.txt
uji_ship.egg-info/dependency_links.txt
uji_ship.egg-info/requires.txt
uji_ship.egg-info/top_level.txt