Metadata-Version: 1.1
Name: uji-ship
Version: 0.1.1
Summary: Python script for building and deploying Java web applications and batch services
Home-page: https://github.com/universitatjaumei/ship
Author: Ricardo Borillo
Author-email: borillo@gmail.com
License: MIT
Keywords: ship setuptools development
Platform: UNKNOWN
Classifier: Development Status :: 3 - Alpha
Classifier: Intended Audience :: Developers
Classifier: Topic :: Software Development :: Build Tools
Classifier: License :: OSI Approved :: MIT License
Classifier: Programming Language :: Python :: 2
Classifier: Programming Language :: Python :: 2.6
Classifier: Programming Language :: Python :: 2.7
